CSNet/__init__.py
CSNet/function.py
CSNet/data/__init__.py
CSNet/data/_utils.py
CSNet/data/config.yaml
CSNet/data/dataset.py
CSNet/data/prepare_data.py
CSNet/experiment/__init__.py
CSNet/experiment/experiment.py
CSNet/model/CSNet.py
CSNet/model/__init__.py
CSNet/model/_criterion.py
CSNet/model/_gumbel.py
CSNet/trainer/__init__.py
CSNet/trainer/trainer.py
CSNet-0.1.8.dist-info/METADATA
CSNet-0.1.8.dist-info/WHEEL
CSNet-0.1.8.dist-info/top_level.txt
CSNet-0.1.8.dist-info/RECORD
