Metadata-Version: 2.1
Name: CSNet
Version: 0.1.8
Summary: short description
Home-page: UNKNOWN
Author: shenzhuoqiao
Author-email: ouc16020021031@gmail.com
License: UNKNOWN
Project-URL: Documentation, https://github.com/ouc16020021031
Project-URL: Code, https://github.com/ouc16020021031
Project-URL: Issue tracker, https://github.com/ouc16020021031
Platform: UNKNOWN
Classifier: Development Status :: 2 - Pre-Alpha
Classifier: Environment :: Console
Classifier: Framework :: Jupyter
Classifier: Intended Audience :: Developers
Classifier: Intended Audience :: Science/Research
Classifier: License :: OSI Approved :: BSD License
Classifier: Operating System :: MacOS :: MacOS X
Classifier: Operating System :: Microsoft :: Windows
Classifier: Operating System :: POSIX :: Linux
Classifier: Programming Language :: Python
Classifier: Programming Language :: Python :: 3.9
Classifier: Topic :: Scientific/Engineering :: Bio-Informatics
Requires-Python: >=3.9
Requires-Dist: scanpy (>=1.8.2)
Requires-Dist: scikit-learn (>=1.0.2)
Requires-Dist: scvi-tools (>=0.15.2)
Requires-Dist: numpy (>=1.20.3)
Requires-Dist: pandas (>=1.3.4)
Requires-Dist: torch (>=1.9.0)
Requires-Dist: pytorch-lightning (>=1.5.7)
Requires-Dist: scipy (>=1.7.1)
Requires-Dist: pyyaml (>=0.2.5)
Requires-Dist: wandb (>=0.12.9)
Requires-Dist: scikit-misc (>=0.1.4)
Requires-Dist: tqdm (>=4.62.3)
Requires-Dist: seaborn (>=0.11.2)
